datamx/__init__.py
datamx/cache/__init__.py
datamx/cache/file_process_cache.py
datamx/models/__init__.py
datamx/models/values.py
datamx/utils/__init__.py
datamx/utils/groups_util.py
datamx/utils/search_utils.py
datamx-0.10.0.dist-info/METADATA
datamx-0.10.0.dist-info/WHEEL
datamx-0.10.0.dist-info/top_level.txt
datamx-0.10.0.dist-info/RECORD
