Metadata-Version: 2.1
Name: datamx
Version: 0.10.0
Summary: data structure for measurements/readings that can hold documentation about them and be read and written to/from objects to json and back
Home-page: https://bitbucket.org/clockworkcodeteam/datamx/src/master/
Author: dilbertau99
Author-email: dilbertau99@gmail.com
License: GNU General Public License V3 or later
Keywords: solar monitoring data format model
Platform: UNKNOWN
Classifier: Programming Language :: Python :: 3
Classifier: License :: OSI Approved :: GNU General Public License v3 or later (GPLv3+)
Classifier: Operating System :: OS Independent
Classifier: Development Status :: 1 - Planning
Classifier: Intended Audience :: End Users/Desktop
Classifier: Natural Language :: English
Classifier: Topic :: Utilities
Classifier: Topic :: Communications
Requires-Dist: marshmallow
Requires-Dist: marshmallow-oneofschema
